meshpro.pyi
meshpro.cpython-38-x86_64-linux-gnu.so
meshpro-0.0.20.dist-info/METADATA
meshpro-0.0.20.dist-info/top_level.txt
meshpro-0.0.20.dist-info/RECORD
meshpro-0.0.20.dist-info/entry_points.txt
meshpro-0.0.20.dist-info/WHEEL
meshpro/_license.pyi
meshpro/_merge.pyi
meshpro/_common.pyi
meshpro/_exceptions.pyi
meshpro/__about__.pyi
meshpro/py.typed
meshpro/_pyvista.pyi
meshpro/_boundary.pyi
meshpro/_submesh.pyi
meshpro/_mesh.pyi
meshpro/__init__.pyi
meshpro/io/_main.pyi
meshpro/io/permas.pyi
meshpro/io/ansys.pyi
meshpro/io/__init__.pyi
meshpro/_cli/_main.pyi
meshpro/_cli/_binary.pyi
meshpro/_cli/_ascii.pyi
meshpro/_cli/_compress.pyi
meshpro/_cli/_decompress.pyi
meshpro/_cli/_convert.pyi
meshpro/_cli/__init__.pyi
