Metadata-Version: 2.1
Name: meshpro
Version: 0.0.20
Summary: Mesh tools for professionals
Home-page: https://github.com/meshpro/support
Author: Nico Schlömer
Author-email: nico.schloemer@gmail.com
License: UNKNOWN
Platform: UNKNOWN
Classifier: Development Status :: 5 - Production/Stable
Classifier: License :: Other/Proprietary License
Classifier: Operating System :: OS Independent
Classifier: Programming Language :: Python :: 3.7
Classifier: Programming Language :: Python :: 3.8
Classifier: Programming Language :: Python :: 3.9
Classifier: Programming Language :: Python :: 3.10
Classifier: Topic :: Scientific/Engineering
Classifier: Topic :: Utilities
Requires-Python: >=3.7
Requires-Dist: appdirs
Requires-Dist: keygen-licensing-tools (>=0.2.0)
Requires-Dist: meshio[all] (>=5.1.1)
Requires-Dist: numpy (>=1.20.0)
Requires-Dist: npx (>=0.0.22)
Requires-Dist: rich
Requires-Dist: tomli
Requires-Dist: tomli-w
Requires-Dist: importlib-metadata ; python_version < "3.8"
Provides-Extra: all
Requires-Dist: pyvista (>=0.33.0) ; extra == 'all'
